[{
    "normal": [0, -1, 0],
    "verts": [[0, 0, 0], [10, 0, 0], [10, 0, 10]]
}, {
    "normal": [0, 1, 0],
    "verts": [[0, 0, 0], [0, 0, 10], [10, 0, 10]]
}, {
    "normal": [1, 0, 0],
    "verts": [[10, 0, 0], [10, 10, 0], [10, 10, 10]]
}, {
    "normal": [-1, 0, 0],
    "verts": [[10, 0, 0], [10, 0, 10], [10, 10, 10]]
}, {
    "normal": [0, 1, 0],
    "verts": [[10, 10, 0], [0, 10, 0], [0, 10, 10]]
}, {
    "normal": [0, -1, 0],
    "verts": [[10, 10, 0], [10, 10, 10], [0, 10, 10]]
}, {
    "normal": [-1, 0, 0],
    "verts": [[0, 10, 0], [0, 0, 0], [0, 0, 10]]
}, {
    "normal": [1, 0, 0],
    "verts": [[0, 10, 0], [0, 10, 10], [0, 0, 10]]
}, [{
    "normal": [0, 0, 0.7071067811865475],
    "verts": [[0, 10, 10], [10, 0, 10], [10, 10, 10]]
}, {
    "normal": [0, 0, 1],
    "verts": [[0, 10, 10], [0, 0, 10], [10, 0, 10]]
}], [{
    "normal": [0, 0, 0.7071067811865475],
    "verts": [[0, 10, 0], [10, 0, 0], [10, 10, 0]]
}, {
    "normal": [0, 0, 1],
    "verts": [[0, 10, 0], [0, 0, 0], [10, 0, 0]]
}]]
